inflow/__init__.py
inflow/inflow.py
python_inflow-1.0.1.dist-info/LICENSE
python_inflow-1.0.1.dist-info/METADATA
python_inflow-1.0.1.dist-info/WHEEL
python_inflow-1.0.1.dist-info/entry_points.txt
python_inflow-1.0.1.dist-info/top_level.txt
python_inflow-1.0.1.dist-info/RECORD
