Metadata-Version: 2.1
Name: python-inflow
Version: 1.0.1
Summary: A variance-optimal paragraph formatter
Author-email: Stephen Huan <stephen.huan@cgdct.moe>
Project-URL: Homepage, https://cgdct.moe/blog/far/
Project-URL: Repository, https://github.com/stephen-huan/inflow
Project-URL: Issues, https://github.com/stephen-huan/inflow/issues
Classifier: Programming Language :: Python :: 3 :: Only
Classifier: License :: OSI Approved :: The Unlicense (Unlicense)
Classifier: Operating System :: OS Independent
Classifier: Topic :: Text Editors :: Text Processing
Classifier: Topic :: Text Processing :: Filters
Requires-Python: >=3.9
License-File: LICENSE
